<?xml version="1.0" encoding="UTF-8"?>
<con:resource xmlns:xsi="http://www.w3.org/2001/XMLSchema-instance" xmlns:con="http://eviware.com/soapui/config" name="removeUserFromGroup" path="api/v1/GroupOperations/removeUserFromGroup" id="eada94f9-4b73-4058-b2c5-78e78cc297f6">
  <con:settings id="9f8a0fa2-9659-40a4-975e-7f485a6c2683">
    <con:setting id="eada94f9-4b73-4058-b2c5-78e78cc297f6fileName">removeUserFromGroup</con:setting>
  </con:settings>
  <con:parameters/>
  <con:method name="Method 1" id="ce81a4c6-86a2-4165-8f40-3140f3c80e89" method="DELETE">
    <con:settings/>
    <con:parameters>
      <con:parameter required="true">
        <con:name>oktaTenantName</con:name>
        <con:value/>
        <con:style>QUERY</con:style>
        <con:default/>
      </con:parameter>
      <con:parameter required="true">
        <con:name>oktaApiKey</con:name>
        <con:value/>
        <con:style>QUERY</con:style>
        <con:default/>
      </con:parameter>
      <con:parameter required="true">
        <con:name>groupName</con:name>
        <con:value/>
        <con:style>QUERY</con:style>
        <con:default/>
      </con:parameter>
      <con:parameter required="true">
        <con:name>userId</con:name>
        <con:value/>
        <con:style>QUERY</con:style>
        <con:default/>
      </con:parameter>
    </con:parameters>
    <con:request name="removeUserFromGroup" id="ef425e12-8b1e-41a6-807b-cdb3d9a20839" mediaType="application/json" postQueryString="false">
      <con:settings>
        <con:setting id="com.eviware.soapui.impl.wsdl.WsdlRequest@request-headers">&lt;xml-fragment/></con:setting>
      </con:settings>
      <con:endpoint>https://10.106.33.36:8089</con:endpoint>
      <con:request/>
      <con:credentials>
        <con:selectedAuthProfile>No Authorization</con:selectedAuthProfile>
        <con:authType>No Authorization</con:authType>
      </con:credentials>
      <con:jmsConfig JMSDeliveryMode="PERSISTENT"/>
      <con:parameters>
        <con:entry key="groupName" value=""/>
        <con:entry key="oktaTenantName" value=""/>
        <con:entry key="userId" value=""/>
      </con:parameters>
      <con:parameterOrder>
        <con:entry>oktaTenantName</con:entry>
        <con:entry>oktaApiKey</con:entry>
        <con:entry>groupName</con:entry>
        <con:entry>userId</con:entry>
      </con:parameterOrder>
    </con:request>
  </con:method>
</con:resource>
